fedbench/__init__.py
fedbench/datasets.py
fedbench/models.py
fedbench/algorithms/__init__.py
fedbench/algorithms/fedadagrad/__init__.py
fedbench/algorithms/fedadagrad/simulation.py
fedbench/algorithms/fedadam/__init__.py
fedbench/algorithms/fedadam/simulation.py
fedbench/algorithms/fedavg/__init__.py
fedbench/algorithms/fedavg/client.py
fedbench/algorithms/fedavg/model_utils.py
fedbench/algorithms/fedavg/simulation.py
fedbench/algorithms/fedbn/__init__.py
fedbench/algorithms/fedbn/client.py
fedbench/algorithms/fedbn/model_utils.py
fedbench/algorithms/fedbn/simulation.py
fedbench/algorithms/fednova/__init__.py
fedbench/algorithms/fednova/client.py
fedbench/algorithms/fednova/model_utils.py
fedbench/algorithms/fednova/server.py
fedbench/algorithms/fednova/simulation.py
fedbench/algorithms/fednova/strategy.py
fedbench/algorithms/fedprox/__init__.py
fedbench/algorithms/fedprox/simulation.py
fedbench/algorithms/fedyogi/__init__.py
fedbench/algorithms/fedyogi/simulation.py
fedbench/algorithms/moon/__init__.py
fedbench/algorithms/moon/client.py
fedbench/algorithms/moon/model_utils.py
fedbench/algorithms/moon/simulation.py
fedbench/algorithms/scaffold/__init__.py
fedbench/algorithms/scaffold/client.py
fedbench/algorithms/scaffold/model_utils.py
fedbench/algorithms/scaffold/server.py
fedbench/algorithms/scaffold/simulation.py
fedbench/algorithms/scaffold/strategy.py
fedbench-0.1.3.dist-info/METADATA
fedbench-0.1.3.dist-info/WHEEL
fedbench-0.1.3.dist-info/top_level.txt
fedbench-0.1.3.dist-info/RECORD
