Metadata-Version: 2.4
Name: fedbench
Version: 0.1.3
Summary: A Federated Learning Benchmarking Framework
Home-page: https://github.com/NechbaMohammed/FLBenchmark
Author: Mohammed Nechba
Author-email: mohammednechba@gmail.com
Classifier: Programming Language :: Python :: 3
Classifier: License :: OSI Approved :: MIT License
Classifier: Operating System :: OS Independent
Classifier: Intended Audience :: Science/Research
Classifier: Topic :: Scientific/Engineering :: Artificial Intelligence
Requires-Python: >=3.7
Requires-Dist: flwr[simulation]==1.16.0
Requires-Dist: omegaconf>=2.1.1
Requires-Dist: torch>=1.10.0
Requires-Dist: torchvision>=0.11.0
Requires-Dist: datasets>=1.18.0
Requires-Dist: hydra-core>=1.1.1
Requires-Dist: scikit-learn>=1.0.0
Requires-Dist: matplotlib>=3.5.0
Provides-Extra: dev
Requires-Dist: pytest>=6.0.0; extra == "dev"
Requires-Dist: black>=21.0; extra == "dev"
Requires-Dist: flake8>=3.9.0; extra == "dev"
Requires-Dist: isort>=5.0.0; extra == "dev"
Dynamic: author
Dynamic: author-email
Dynamic: classifier
Dynamic: description
Dynamic: description-content-type
Dynamic: home-page
Dynamic: provides-extra
Dynamic: requires-dist
Dynamic: requires-python
Dynamic: summary
